luminadb/__init__.py
luminadb/_debug.py
luminadb/column.py
luminadb/csv.py
luminadb/database.py
luminadb/errors.py
luminadb/functions.py
luminadb/index.py
luminadb/locals.py
luminadb/operators.py
luminadb/signature.py
luminadb/subquery.py
luminadb/table.py
luminadb/typings.py
luminadb/utils.py
luminadb/models/__init__.py
luminadb/models/errors.py
luminadb/models/helpers.py
luminadb/models/mixin.py
luminadb/models/query_builder.py
luminadb/models/type_checkers.py
luminadb/query_builder/__init__.py
luminadb/query_builder/core.py
luminadb/query_builder/engine.py
luminadb/query_builder/table_creation.py
luminadb/query_builder/typings.py
luminadb/query_builder/utils.py
luminadb/workers/__init__.py
luminadb/workers/connection.py
luminadb/workers/database.py
luminadb/workers/worker.py
luminadb-0.7.14.dist-info/licenses/LICENSE
luminadb-0.7.14.dist-info/METADATA
luminadb-0.7.14.dist-info/WHEEL
luminadb-0.7.14.dist-info/top_level.txt
luminadb-0.7.14.dist-info/zip-safe
luminadb-0.7.14.dist-info/RECORD
